README.md
setup.cfg
setup.py
gift_distributions/Binomialdistribution.py
gift_distributions/Gaussiandistribution.py
gift_distributions/Generaldistribution.py
gift_distributions/__init__.py
prpgifttest_distributions.egg-info/PKG-INFO
prpgifttest_distributions.egg-info/SOURCES.txt
prpgifttest_distributions.egg-info/dependency_links.txt
prpgifttest_distributions.egg-info/not-zip-safe
prpgifttest_distributions.egg-info/top_level.txt